cypackage/__init__.py
cypackage/cypackage.py
cypackage-1.0.dist-info/METADATA
cypackage-1.0.dist-info/WHEEL
cypackage-1.0.dist-info/entry_points.txt
cypackage-1.0.dist-info/top_level.txt
cypackage-1.0.dist-info/RECORD
