Metadata-Version: 2.1
Name: cypackage
Version: 1.0
Summary: This is a console script that used to easily generate cython base on your package.
Home-page: https://github.com/aminor-z/cypackage
Author: Aminor_z
Author-email: aminor_z@qq.com
License: MIT
Keywords: cython
Platform: UNKNOWN
Requires-Dist: easycython
Requires-Dist: cython
Requires-Dist: numpy
Requires-Dist: begins
